Workbook
Name ListaBarberos: Config!$A$5:$A$10
Name ListaEstados: Config!$J$5:$J$7
Name ListaMetodos: Config!$H$5:$H$13
Name ListaServicios: Config!$D$5:$D$24

Sheet Instrucciones
B1: RIIF — CONTROL DE BARBERÍA · Registro, caja, comisiones y rentabilidad
B3: CÓMO FUNCIONA
B4: Una sola fuente de verdad: la hoja REGISTRO. Una fila = un servicio prestado.
B5: Cierre diario, comisiones y análisis se calculan solos desde ahí. No se digita nada dos veces.
B7: ORDEN DE USO
B8: 1. CONFIG: pon los nombres reales de tus 2 barberos y su % de comisión. Tu carta de servicios ya está cargada con precios y duraciones.
B9: 2. REGISTRO: se anota cada servicio (lo alimentan los barberos vía formulario, tú solo lees).
B10: 3. CIERRE DIARIO: escribes una fecha y sale la caja del día, el desglose por medio de pago y lo que le debes a cada barbero.
B11: 4. COMISIONES: año y mes, y sale la liquidación.
B12: 5. ANÁLISIS: el histórico. Qué servicio rinde más POR HORA de silla, qué días y horas se llenan, quién produce.
B14: QUÉ CELDAS TOCAS
B15: AZUL sobre amarillo = escribes ahí. · NEGRO sobre gris = fórmula, no la toques.
... B40: · Preparado para 1.000 servicios. Al llenarse, copia las fórmulas hacia abajo.

Sheet Config
A1: CONFIGURACIÓN
A2: Los servicios y precios ya están cargados desde tu carta. Solo faltan los nombres de los barberos.
A3: BARBEROS | D3: SERVICIOS, PRECIOS Y DURACIÓN | H3: MÉTODOS DE PAGO | J3: ESTADOS
A4: Nombre | B4: % Comisión | D4: Servicio | E4: Precio | F4: Duración (min) | H4: Método | J4: Estado
A5: Rafael Castro | B5: 0.5 | D5: Tinte (cambio de color) | E5: 180000 | F5: 130 | H5: Efectivo | J5: Atendido
A6: Daniel Avila | B6: 0.5 | D6: Corte y Barba Riif Experience | E6: 110000 | F6: 80 | H6: Nequi | J6: No asistió
D7: Corte y Barba VIP | E7: 85000 | F7: 75 | H7: Daviplata | J7: Cancelado
D8: Tinte un Color | E8: 80000 | F8: 45 | H8: Tarjeta débito
D9: Corte Riif Experience | E9: 75000 | F9: 90 | H9: Tarjeta crédito
D10: Tratamiento facial | E10: 60000 | F10: 60 | H10: Transferencia
D11: Corte y Barba | E11: 60000 | F11: 45 | H11: Bold / Datáfono
D12: Corte VIP | E12: 50000 | F12: 50
A13: El % de comisión se aplica sobre el valor cobrado del servicio, sin propina. | D13: Matizante | E13: 45000 | F13: 30
D14: Barba VIP | E14: 40000 | F14: 40
D15: Barba + Tinte | E15: 40000 | F15: 30 | H15: No borres 'Atendido' de Estados:
D16: Corte de Cabello | E16: 35000 | F16: 35 | H16: los cálculos dependen de ese texto.
D17: Barba | E17: 25000 | F17: 25
D18: Mascarilla puntos negros | E18: 20000 | F18: 25
D19: Peinado | E19: 20000 | F19: 15
D20: Bordes / Line-up | E20: 15000 | F20: 20
D21: Cejas | E21: 10000 | F21: 15
D26: Duraciones tomadas de tu carta. Son las que alimentan el cálculo de ingreso por hora de silla.

Sheet Reservas
A1: ID | B1: Creado | C1: Fecha | D1: Hora inicio | E1: Hora fin | F1: Barbero | G1: Servicio | H1: Duración (min) | I1: Precio | J1: Cliente | K1: Teléfono | L1: Email | M1: Estado | N1: Notas | O1: ID Evento | P1: Avisar al barbero

Sheet Bloqueos
A1: Barbero | B1: Fecha | C1: Desde | D1: Hasta | E1: Motivo
A3: Usa "Todos" en Barbero para cerrar el local completo ese rato.

Sheet Horarios
A1: Barbero | B1: Día | C1: Abre | D1: Cierra
A2: Barbero 1 | B2: Lunes | C2: 10:00 | D2: 19:00
A3: Barbero 1 | B3: Martes | C3: 10:00 | D3: 19:00
A4: Barbero 1 | B4: Miércoles | C4: 10:00 | D4: 19:00
A5: Barbero 1 | B5: Jueves | C5: 10:00 | D5: 19:00
A6: Barbero 1 | B6: Viernes | C6: 10:00 | D6: 19:00
A7: Barbero 1 | B7: Sábado | C7: 10:00 | D7: 19:00
A8: Barbero 2 | B8: Lunes | C8: 10:00 | D8: 19:00
A9: Barbero 2 | B9: Martes | C9: 10:00 | D9: 19:00
A10: Barbero 2 | B10: Miércoles | C10: 10:00 | D10: 19:00
A11: Barbero 2 | B11: Jueves | C11: 10:00 | D11: 19:00
A12: Barbero 2 | B12: Viernes | C12: 10:00 | D12: 19:00
A13: Barbero 2 | B13: Sábado | C13: 10:00 | D13: 19:00

Sheet Barberos
A1: Nombre | B1: Correo (Gmail) | C1: WhatsApp | D1: API key WhatsApp | E1: ID Calendario | F1: Notificar
A2: Rafael Castro | B2: castroramirezrafael@gmail.com | C2: 573023931317 | E2: 4edfee79d2ee807bf38c4c025a5816176cb050b32ab3a496088f75cf4e0e9604@group.calendar.google.com | F2: Sí
A3: Daniel Avila | B3: avilaparracarlosdaniel@gmail.com | C3: 573001266321 | E3: ca3d6a08d3b68aaba22ce1dc60b7acd075d21dfd274f03149d95608de484821f@group.calendar.google.com | F3: Sí
A4: Riif Reservas | E4: c3af741d23bce4618e828b631bbd643d96d0fe902424989351e5ed80212c5465@group.calendar.google.com

Sheet Registro
A1: Fecha | B1: Hora | C1: Barbero | D1: Cliente | E1: Teléfono | F1: Servicio | G1: Valor servicio | H1: Descuento | I1: Total cobrado | J1: Propina | K1: Método de pago | L1: Estado | M1: Comisión servicio | N1: Pago al barbero | O1: Neto barbería | P1: Notas | Q1: Año | R1: Mes | S1: Día semana | T1: Hora bloque | U1: Duración (min)
A2: 46239 | B2: 0.64583333 | C2: Barbero 1 | D2: Andrés Pérez | E2: 3005551234 | F2: Corte y Barba VIP | G2: {=IF($F2="","",IFERROR(INDEX(Config!$E:$E,MATCH($F2,Config!$D:$D,0)),0))} -> 85000 | I2: =IF($F2="","",$G2-IF($H2="",0,$H2)) -> 85000 | K2: Efectivo | L2: Atendido | M2: {=IF($A2="","",IF($L2="Atendido",IFERROR($I2*INDEX(Config!$B:$B,MATCH($C2,Config!$A:$A,0)),0),0))} -> 0 | N2: =IF($A2="","",IF($L2="Atendido",$M2+IF($J2="",0,$J2),0)) -> 0 | O2: =IF($A2="","",IF($L2="Atendido",$I2-$M2,0)) -> 85000 | P2: EJEMPLO — BORRAR ESTA FILA | Q2: =IF($A2="","",YEAR($A2)) -> 2026 | R2: =IF($A2="","",MONTH($A2)) -> 8 | S2: =IF($A2="","",CHOOSE(WEEKDAY($A2,2),"Lunes","Martes","Miércoles","Jueves","Viernes","Sábado","Domingo")) -> Miércoles | T2: =IF($B2="","",HOUR($B2)) -> 15 | U2: {=IF($F2="","",IFERROR(INDEX(Config!$F:$F,MATCH($F2,Config!$D:$D,0)),0))} -> 75
G3: {=IF($F3="","",IFERROR(INDEX(Config!$E:$E,MATCH($F3,Config!$D:$D,0)),0))} | I3: =IF($F3="","",$G3-IF($H3="",0,$H3)) | M3: {=IF($A3="","",IF($L3="Atendido",IFERROR($I3*INDEX(Config!$B:$B,MATCH($C3,Config!$A:$A,0)),0),0))} | N3: =IF($A3="","",IF($L3="Atendido",$M3+IF($J3="",0,$J3),0)) | O3: =IF($A3="","",IF($L3="Atendido",$I3-$M3,0)) | Q3: =IF($A3="","",YEAR($A3)) | R3: =IF($A3="","",MONTH($A3)) | S3: =IF($A3="","",CHOOSE(WEEKDAY($A3,2),"Lunes","Martes","Miércoles","Jueves","Viernes","Sábado","Domingo")) | T3: =IF($B3="","",HOUR($B3)) | U3: {=IF($F3="","",IFERROR(INDEX(Config!$F:$F,MATCH($F3,Config!$D:$D,0)),0))}
G4: {=IF($F4="","",IFERROR(INDEX(Config!$E:$E,MATCH($F4,Config!$D:$D,0)),0))} | I4: =IF($F4="","",$G4-IF($H4="",0,$H4)) | M4: {=IF($A4="","",IF($L4="Atendido",IFERROR($I4*INDEX(Config!$B:$B,MATCH($C4,Config!$A:$A,0)),0),0))} | N4: =IF($A4="","",IF($L4="Atendido",$M4+IF($J4="",0,$J4),0)) | O4: =IF($A4="","",IF($L4="Atendido",$I4-$M4,0)) | Q4: =IF($A4="","",YEAR($A4)) | R4: =IF($A4="","",MONTH($A4)) | S4: =IF($A4="","",CHOOSE(WEEKDAY($A4,2),"Lunes","Martes","Miércoles","Jueves","Viernes","Sábado","Domingo")) | T4: =IF($B4="","",HOUR($B4)) | U4: {=IF($F4="","",IFERROR(INDEX(Config!$F:$F,MATCH($F4,Config!$D:$D,0)),0))}
G5: {=IF($F5="","",IFERROR(INDEX(Config!$E:$E,MATCH($F5,Config!$D:$D,0)),0))} | I5: =IF($F5="","",$G5-IF($H5="",0,$H5)) | M5: {=IF($A5="","",IF($L5="Atendido",IFERROR($I5*INDEX(Config!$B:$B,MATCH($C5,Config!$A:$A,0)),0),0))} | N5: =IF($A5="","",IF($L5="Atendido",$M5+IF($J5="",0,$J5),0)) | O5: =IF($A5="","",IF($L5="Atendido",$I5-$M5,0)) | Q5: =IF($A5="","",YEAR($A5)) | R5: =IF($A5="","",MONTH($A5)) | S5: =IF($A5="","",CHOOSE(WEEKDAY($A5,2),"Lunes","Martes","Miércoles","Jueves","Viernes","Sábado","Domingo")) | T5: =IF($B5="","",HOUR($B5)) | U5: {=IF($F5="","",IFERROR(INDEX(Config!$F:$F,MATCH($F5,Config!$D:$D,0)),0))}
G6: {=IF($F6="","",IFERROR(INDEX(Config!$E:$E,MATCH($F6,Config!$D:$D,0)),0))} | I6: =IF($F6="","",$G6-IF($H6="",0,$H6)) | M6: {=IF($A6="","",IF($L6="Atendido",IFERROR($I6*INDEX(Config!$B:$B,MATCH($C6,Config!$A:$A,0)),0),0))} | N6: =IF($A6="","",IF($L6="Atendido",$M6+IF($J6="",0,$J6),0)) | O6: =IF($A6="","",IF($L6="Atendido",$I6-$M6,0)) | Q6: =IF($A6="","",YEAR($A6)) | R6: =IF($A6="","",MONTH($A6)) | S6: =IF($A6="","",CHOOSE(WEEKDAY($A6,2),"Lunes","Martes","Miércoles","Jueves","Viernes","Sábado","Domingo")) | T6: =IF($B6="","",HOUR($B6)) | U6: {=IF($F6="","",IFERROR(INDEX(Config!$F:$F,MATCH($F6,Config!$D:$D,0)),0))}
G7: {=IF($F7="","",IFERROR(INDEX(Config!$E:$E,MATCH($F7,Config!$D:$D,0)),0))} | I7: =IF($F7="","",$G7-IF($H7="",0,$H7)) | M7: {=IF($A7="","",IF($L7="Atendido",IFERROR($I7*INDEX(Config!$B:$B,MATCH($C7,Config!$A:$A,0)),0),0))} | N7: =IF($A7="","",IF($L7="Atendido",$M7+IF($J7="",0,$J7),0)) | O7: =IF($A7="","",IF($L7="Atendido",$I7-$M7,0)) | Q7: =IF($A7="","",YEAR($A7)) | R7: =IF($A7="","",MONTH($A7)) | S7: =IF($A7="","",CHOOSE(WEEKDAY($A7,2),"Lunes","Martes","Miércoles","Jueves","Viernes","Sábado","Domingo")) | T7: =IF($B7="","",HOUR($B7)) | U7: {=IF($F7="","",IFERROR(INDEX(Config!$F:$F,MATCH($F7,Config!$D:$D,0)),0))}
G8: {=IF($F8="","",IFERROR(INDEX(Config!$E:$E,MATCH($F8,Config!$D:$D,0)),0))} | I8: =IF($F8="","",$G8-IF($H8="",0,$H8)) | M8: {=IF($A8="","",IF($L8="Atendido",IFERROR($I8*INDEX(Config!$B:$B,MATCH($C8,Config!$A:$A,0)),0),0))} | N8: =IF($A8="","",IF($L8="Atendido",$M8+IF($J8="",0,$J8),0)) | O8: =IF($A8="","",IF($L8="Atendido",$I8-$M8,0)) | Q8: =IF($A8="","",YEAR($A8)) | R8: =IF($A8="","",MONTH($A8)) | S8: =IF($A8="","",CHOOSE(WEEKDAY($A8,2),"Lunes","Martes","Miércoles","Jueves","Viernes","Sábado","Domingo")) | T8: =IF($B8="","",HOUR($B8)) | U8: {=IF($F8="","",IFERROR(INDEX(Config!$F:$F,MATCH($F8,Config!$D:$D,0)),0))}
G9: {=IF($F9="","",IFERROR(INDEX(Config!$E:$E,MATCH($F9,Config!$D:$D,0)),0))} | I9: =IF($F9="","",$G9-IF($H9="",0,$H9)) | M9: {=IF($A9="","",IF($L9="Atendido",IFERROR($I9*INDEX(Config!$B:$B,MATCH($C9,Config!$A:$A,0)),0),0))} | N9: =IF($A9="","",IF($L9="Atendido",$M9+IF($J9="",0,$J9),0)) | O9: =IF($A9="","",IF($L9="Atendido",$I9-$M9,0)) | Q9: =IF($A9="","",YEAR($A9)) | R9: =IF($A9="","",MONTH($A9)) | S9: =IF($A9="","",CHOOSE(WEEKDAY($A9,2),"Lunes","Martes","Miércoles","Jueves","Viernes","Sábado","Domingo")) | T9: =IF($B9="","",HOUR($B9)) | U9: {=IF($F9="","",IFERROR(INDEX(Config!$F:$F,MATCH($F9,Config!$D:$D,0)),0))}
G10: {=IF($F10="","",IFERROR(INDEX(Config!$E:$E,MATCH($F10,Config!$D:$D,0)),0))} | I10: =IF($F10="","",$G10-IF($H10="",0,$H10)) | M10: {=IF($A10="","",IF($L10="Atendido",IFERROR($I10*INDEX(Config!$B:$B,MATCH($C10,Config!$A:$A,0)),0),0))} | N10: =IF($A10="","",IF($L10="Atendido",$M10+IF($J10="",0,$J10),0)) | O10: =IF($A10="","",IF($L10="Atendido",$I10-$M10,0)) | Q10: =IF($A10="","",YEAR($A10)) | R10: =IF($A10="","",MONTH($A10)) | S10: =IF($A10="","",CHOOSE(WEEKDAY($A10,2),"Lunes","Martes","Miércoles","Jueves","Viernes","Sábado","Domingo")) | T10: =IF($B10="","",HOUR($B10)) | U10: {=IF($F10="","",IFERROR(INDEX(Config!$F:$F,MATCH($F10,Config!$D:$D,0)),0))}
G11: {=IF($F11="","",IFERROR(INDEX(Config!$E:$E,MATCH($F11,Config!$D:$D,0)),0))} | I11: =IF($F11="","",$G11-IF($H11="",0,$H11)) | M11: {=IF($A11="","",IF($L11="Atendido",IFERROR($I11*INDEX(Config!$B:$B,MATCH($C11,Config!$A:$A,0)),0),0))} | N11: =IF($A11="","",IF($L11="Atendido",$M11+IF($J11="",0,$J11),0)) | O11: =IF($A11="","",IF($L11="Atendido",$I11-$M11,0)) | Q11: =IF($A11="","",YEAR($A11)) | R11: =IF($A11="","",MONTH($A11)) | S11: =IF($A11="","",CHOOSE(WEEKDAY($A11,2),"Lunes","Martes","Miércoles","Jueves","Viernes","Sábado","Domingo")) | T11: =IF($B11="","",HOUR($B11)) | U11: {=IF($F11="","",IFERROR(INDEX(Config!$F:$F,MATCH($F11,Config!$D:$D,0)),0))}
G12: {=IF($F12="","",IFERROR(INDEX(Config!$E:$E,MATCH($F12,Config!$D:$D,0)),0))} | I12: =IF($F12="","",$G12-IF($H12="",0,$H12)) | M12: {=IF($A12="","",IF($L12="Atendido",IFERROR($I12*INDEX(Config!$B:$B,MATCH($C12,Config!$A:$A,0)),0),0))} | N12: =IF($A12="","",IF($L12="Atendido",$M12+IF($J12="",0,$J12),0)) | O12: =IF($A12="","",IF($L12="Atendido",$I12-$M12,0)) | Q12: =IF($A12="","",YEAR($A12)) | R12: =IF($A12="","",MONTH($A12)) | S12: =IF($A12="","",CHOOSE(WEEKDAY($A12,2),"Lunes","Martes","Miércoles","Jueves","Viernes","Sábado","Domingo")) | T12: =IF($B12="","",HOUR($B12)) | U12: {=IF($F12="","",IFERROR(INDEX(Config!$F:$F,MATCH($F12,Config!$D:$D,0)),0))}
G13: {=IF($F13="","",IFERROR(INDEX(Config!$E:$E,MATCH($F13,Config!$D:$D,0)),0))} | I13: =IF($F13="","",$G13-IF($H13="",0,$H13)) | M13: {=IF($A13="","",IF($L13="Atendido",IFERROR($I13*INDEX(Config!$B:$B,MATCH($C13,Config!$A:$A,0)),0),0))} | N13: =IF($A13="","",IF($L13="Atendido",$M13+IF($J13="",0,$J13),0)) | O13: =IF($A13="","",IF($L13="Atendido",$I13-$M13,0)) | Q13: =IF($A13="","",YEAR($A13)) | R13: =IF($A13="","",MONTH($A13)) | S13: =IF($A13="","",CHOOSE(WEEKDAY($A13,2),"Lunes","Martes","Miércoles","Jueves","Viernes","Sábado","Domingo")) | T13: =IF($B13="","",HOUR($B13)) | U13: {=IF($F13="","",IFERROR(INDEX(Config!$F:$F,MATCH($F13,Config!$D:$D,0)),0))}
G14: {=IF($F14="","",IFERROR(INDEX(Config!$E:$E,MATCH($F14,Config!$D:$D,0)),0))} | I14: =IF($F14="","",$G14-IF($H14="",0,$H14)) | M14: {=IF($A14="","",IF($L14="Atendido",IFERROR($I14*INDEX(Config!$B:$B,MATCH($C14,Config!$A:$A,0)),0),0))} | N14: =IF($A14="","",IF($L14="Atendido",$M14+IF($J14="",0,$J14),0)) | O14: =IF($A14="","",IF($L14="Atendido",$I14-$M14,0)) | Q14: =IF($A14="","",YEAR($A14)) | R14: =IF($A14="","",MONTH($A14)) | S14: =IF($A14="","",CHOOSE(WEEKDAY($A14,2),"Lunes","Martes","Miércoles","Jueves","Viernes","Sábado","Domingo")) | T14: =IF($B14="","",HOUR($B14)) | U14: {=IF($F14="","",IFERROR(INDEX(Config!$F:$F,MATCH($F14,Config!$D:$D,0)),0))}
... G3000: {=IF($F3000="","",IFERROR(INDEX(Config!$E:$E,MATCH($F3000,Config!$D:$D,0)),0))} | I3000: =IF($F3000="","",$G3000-IF($H3000="",0,$H3000)) | M3000: {=IF($A3000="","",IF($L3000="Atendido",IFERROR($I3000*INDEX(Config!$B:$B,MATCH($C3000,Config!$A:$A,0)),0),0))} | N3000: =IF($A3000="","",IF($L3000="Atendido",$M3000+IF($J3000="",0,$J3000),0)) | O3000: =IF($A3000="","",IF($L3000="Atendido",$I3000-$M3000,0)) | Q3000: =IF($A3000="","",YEAR($A3000)) | R3000: =IF($A3000="","",MONTH($A3000)) | S3000: =IF($A3000="","",CHOOSE(WEEKDAY($A3000,2),"Lunes","Martes","Miércoles","Jueves","Viernes","Sábado","Domingo")) | T3000: =IF($B3000="","",HOUR($B3000)) | U3000: {=IF($F3000="","",IFERROR(INDEX(Config!$F:$F,MATCH($F3000,Config!$D:$D,0)),0))}

Sheet Cierre diario
B1: CIERRE DIARIO
B3: Fecha a consultar: | C3: 46241
B5: PRODUCCIÓN POR BARBERO
B6: Barbero | C6: Servicios | D6: Producido | E6: Propinas | F6: Comisión | G6: Pago al barbero | H6: Neto barbería | I6: Horas en silla
B7: =IF(Config!$A$5="","",Config!$A$5) -> Rafael Castro | C7: =IF($B7="","",COUNTIFS(Registro!$A$2:$A$3001,$C$3,Registro!$C$2:$C$3001,$B7,Registro!$L$2:$L$3001,"Atendido")) -> 0 | D7: =IF($B7="","",SUMIFS(Registro!$I$2:$I$3001,Registro!$A$2:$A$3001,$C$3,Registro!$C$2:$C$3001,$B7,Registro!$L$2:$L$3001,"Atendido")) -> 0 | E7: =IF($B7="","",SUMIFS(Registro!$J$2:$J$3001,Registro!$A$2:$A$3001,$C$3,Registro!$C$2:$C$3001,$B7,Registro!$L$2:$L$3001,"Atendido")) -> 0 | F7: =IF($B7="","",SUMIFS(Registro!$M$2:$M$3001,Registro!$A$2:$A$3001,$C$3,Registro!$C$2:$C$3001,$B7)) -> 0 | G7: =IF($B7="","",SUMIFS(Registro!$N$2:$N$3001,Registro!$A$2:$A$3001,$C$3,Registro!$C$2:$C$3001,$B7)) -> 0 | H7: =IF($B7="","",SUMIFS(Registro!$O$2:$O$3001,Registro!$A$2:$A$3001,$C$3,Registro!$C$2:$C$3001,$B7)) -> 0 | I7: =IF($B7="","",SUMIFS(Registro!$U$2:$U$3001,Registro!$A$2:$A$3001,$C$3,Registro!$C$2:$C$3001,$B7,Registro!$L$2:$L$3001,"Atendido")/60) -> 0
B8: =IF(Config!$A$6="","",Config!$A$6) -> Daniel Avila | C8: =IF($B8="","",COUNTIFS(Registro!$A$2:$A$3001,$C$3,Registro!$C$2:$C$3001,$B8,Registro!$L$2:$L$3001,"Atendido")) -> 0 | D8: =IF($B8="","",SUMIFS(Registro!$I$2:$I$3001,Registro!$A$2:$A$3001,$C$3,Registro!$C$2:$C$3001,$B8,Registro!$L$2:$L$3001,"Atendido")) -> 0 | E8: =IF($B8="","",SUMIFS(Registro!$J$2:$J$3001,Registro!$A$2:$A$3001,$C$3,Registro!$C$2:$C$3001,$B8,Registro!$L$2:$L$3001,"Atendido")) -> 0 | F8: =IF($B8="","",SUMIFS(Registro!$M$2:$M$3001,Registro!$A$2:$A$3001,$C$3,Registro!$C$2:$C$3001,$B8)) -> 0 | G8: =IF($B8="","",SUMIFS(Registro!$N$2:$N$3001,Registro!$A$2:$A$3001,$C$3,Registro!$C$2:$C$3001,$B8)) -> 0 | H8: =IF($B8="","",SUMIFS(Registro!$O$2:$O$3001,Registro!$A$2:$A$3001,$C$3,Registro!$C$2:$C$3001,$B8)) -> 0 | I8: =IF($B8="","",SUMIFS(Registro!$U$2:$U$3001,Registro!$A$2:$A$3001,$C$3,Registro!$C$2:$C$3001,$B8,Registro!$L$2:$L$3001,"Atendido")/60) -> 0
B9: =IF(Config!$A$7="","",Config!$A$7) | C9: =IF($B9="","",COUNTIFS(Registro!$A$2:$A$3001,$C$3,Registro!$C$2:$C$3001,$B9,Registro!$L$2:$L$3001,"Atendido")) | D9: =IF($B9="","",SUMIFS(Registro!$I$2:$I$3001,Registro!$A$2:$A$3001,$C$3,Registro!$C$2:$C$3001,$B9,Registro!$L$2:$L$3001,"Atendido")) | E9: =IF($B9="","",SUMIFS(Registro!$J$2:$J$3001,Registro!$A$2:$A$3001,$C$3,Registro!$C$2:$C$3001,$B9,Registro!$L$2:$L$3001,"Atendido")) | F9: =IF($B9="","",SUMIFS(Registro!$M$2:$M$3001,Registro!$A$2:$A$3001,$C$3,Registro!$C$2:$C$3001,$B9)) | G9: =IF($B9="","",SUMIFS(Registro!$N$2:$N$3001,Registro!$A$2:$A$3001,$C$3,Registro!$C$2:$C$3001,$B9)) | H9: =IF($B9="","",SUMIFS(Registro!$O$2:$O$3001,Registro!$A$2:$A$3001,$C$3,Registro!$C$2:$C$3001,$B9)) | I9: =IF($B9="","",SUMIFS(Registro!$U$2:$U$3001,Registro!$A$2:$A$3001,$C$3,Registro!$C$2:$C$3001,$B9,Registro!$L$2:$L$3001,"Atendido")/60)
B10: =IF(Config!$A$8="","",Config!$A$8) | C10: =IF($B10="","",COUNTIFS(Registro!$A$2:$A$3001,$C$3,Registro!$C$2:$C$3001,$B10,Registro!$L$2:$L$3001,"Atendido")) | D10: =IF($B10="","",SUMIFS(Registro!$I$2:$I$3001,Registro!$A$2:$A$3001,$C$3,Registro!$C$2:$C$3001,$B10,Registro!$L$2:$L$3001,"Atendido")) | E10: =IF($B10="","",SUMIFS(Registro!$J$2:$J$3001,Registro!$A$2:$A$3001,$C$3,Registro!$C$2:$C$3001,$B10,Registro!$L$2:$L$3001,"Atendido")) | F10: =IF($B10="","",SUMIFS(Registro!$M$2:$M$3001,Registro!$A$2:$A$3001,$C$3,Registro!$C$2:$C$3001,$B10)) | G10: =IF($B10="","",SUMIFS(Registro!$N$2:$N$3001,Registro!$A$2:$A$3001,$C$3,Registro!$C$2:$C$3001,$B10)) | H10: =IF($B10="","",SUMIFS(Registro!$O$2:$O$3001,Registro!$A$2:$A$3001,$C$3,Registro!$C$2:$C$3001,$B10)) | I10: =IF($B10="","",SUMIFS(Registro!$U$2:$U$3001,Registro!$A$2:$A$3001,$C$3,Registro!$C$2:$C$3001,$B10,Registro!$L$2:$L$3001,"Atendido")/60)
B11: =IF(Config!$A$9="","",Config!$A$9) | C11: =IF($B11="","",COUNTIFS(Registro!$A$2:$A$3001,$C$3,Registro!$C$2:$C$3001,$B11,Registro!$L$2:$L$3001,"Atendido")) | D11: =IF($B11="","",SUMIFS(Registro!$I$2:$I$3001,Registro!$A$2:$A$3001,$C$3,Registro!$C$2:$C$3001,$B11,Registro!$L$2:$L$3001,"Atendido")) | E11: =IF($B11="","",SUMIFS(Registro!$J$2:$J$3001,Registro!$A$2:$A$3001,$C$3,Registro!$C$2:$C$3001,$B11,Registro!$L$2:$L$3001,"Atendido")) | F11: =IF($B11="","",SUMIFS(Registro!$M$2:$M$3001,Registro!$A$2:$A$3001,$C$3,Registro!$C$2:$C$3001,$B11)) | G11: =IF($B11="","",SUMIFS(Registro!$N$2:$N$3001,Registro!$A$2:$A$3001,$C$3,Registro!$C$2:$C$3001,$B11)) | H11: =IF($B11="","",SUMIFS(Registro!$O$2:$O$3001,Registro!$A$2:$A$3001,$C$3,Registro!$C$2:$C$3001,$B11)) | I11: =IF($B11="","",SUMIFS(Registro!$U$2:$U$3001,Registro!$A$2:$A$3001,$C$3,Registro!$C$2:$C$3001,$B11,Registro!$L$2:$L$3001,"Atendido")/60)
B12: =IF(Config!$A$10="","",Config!$A$10) | C12: =IF($B12="","",COUNTIFS(Registro!$A$2:$A$3001,$C$3,Registro!$C$2:$C$3001,$B12,Registro!$L$2:$L$3001,"Atendido")) | D12: =IF($B12="","",SUMIFS(Registro!$I$2:$I$3001,Registro!$A$2:$A$3001,$C$3,Registro!$C$2:$C$3001,$B12,Registro!$L$2:$L$3001,"Atendido")) | E12: =IF($B12="","",SUMIFS(Registro!$J$2:$J$3001,Registro!$A$2:$A$3001,$C$3,Registro!$C$2:$C$3001,$B12,Registro!$L$2:$L$3001,"Atendido")) | F12: =IF($B12="","",SUMIFS(Registro!$M$2:$M$3001,Registro!$A$2:$A$3001,$C$3,Registro!$C$2:$C$3001,$B12)) | G12: =IF($B12="","",SUMIFS(Registro!$N$2:$N$3001,Registro!$A$2:$A$3001,$C$3,Registro!$C$2:$C$3001,$B12)) | H12: =IF($B12="","",SUMIFS(Registro!$O$2:$O$3001,Registro!$A$2:$A$3001,$C$3,Registro!$C$2:$C$3001,$B12)) | I12: =IF($B12="","",SUMIFS(Registro!$U$2:$U$3001,Registro!$A$2:$A$3001,$C$3,Registro!$C$2:$C$3001,$B12,Registro!$L$2:$L$3001,"Atendido")/60)
B13: TOTAL DÍA | C13: =SUM(C7:C12) -> 0 | D13: =SUM(D7:D12) -> 0 | E13: =SUM(E7:E12) -> 0 | F13: =SUM(F7:F12) -> 0 | G13: =SUM(G7:G12) -> 0 | H13: =SUM(H7:H12) -> 0 | I13: =SUM(I7:I12) -> 0
B15: CAJA POR MÉTODO DE PAGO | F15: CITAS PERDIDAS DEL DÍA
B16: Método | C16: Servicios | D16: Recaudado | F16: No asistió | G16: =COUNTIFS(Registro!$A$2:$A$3001,$C$3,Registro!$L$2:$L$3001,"No asistió") -> 0
B17: =IF(Config!$H$5="","",Config!$H$5) -> Efectivo | C17: =IF($B17="","",COUNTIFS(Registro!$A$2:$A$3001,$C$3,Registro!$K$2:$K$3001,$B17,Registro!$L$2:$L$3001,"Atendido")) -> 0 | D17: =IF($B17="","",SUMIFS(Registro!$I$2:$I$3001,Registro!$A$2:$A$3001,$C$3,Registro!$K$2:$K$3001,$B17,Registro!$L$2:$L$3001,"Atendido")+SUMIFS(Registro!$J$2:$J$3001,Registro!$A$2:$A$3001,$C$3,Registro!$K$2:$K$3001,$B17,Registro!$L$2:$L$3001,"Atendido")) -> 0 | F17: Cancelado | G17: =COUNTIFS(Registro!$A$2:$A$3001,$C$3,Registro!$L$2:$L$3001,"Cancelado") -> 0
B18: =IF(Config!$H$6="","",Config!$H$6) -> Nequi | C18: =IF($B18="","",COUNTIFS(Registro!$A$2:$A$3001,$C$3,Registro!$K$2:$K$3001,$B18,Registro!$L$2:$L$3001,"Atendido")) -> 0 | D18: =IF($B18="","",SUMIFS(Registro!$I$2:$I$3001,Registro!$A$2:$A$3001,$C$3,Registro!$K$2:$K$3001,$B18,Registro!$L$2:$L$3001,"Atendido")+SUMIFS(Registro!$J$2:$J$3001,Registro!$A$2:$A$3001,$C$3,Registro!$K$2:$K$3001,$B18,Registro!$L$2:$L$3001,"Atendido")) -> 0 | F18: Valor no realizado | G18: =SUMIFS(Registro!$I$2:$I$3001,Registro!$A$2:$A$3001,$C$3,Registro!$L$2:$L$3001,"No asistió")+SUMIFS(Registro!$I$2:$I$3001,Registro!$A$2:$A$3001,$C$3,Registro!$L$2:$L$3001,"Cancelado") -> 0
B19: =IF(Config!$H$7="","",Config!$H$7) -> Daviplata | C19: =IF($B19="","",COUNTIFS(Registro!$A$2:$A$3001,$C$3,Registro!$K$2:$K$3001,$B19,Registro!$L$2:$L$3001,"Atendido")) -> 0 | D19: =IF($B19="","",SUMIFS(Registro!$I$2:$I$3001,Registro!$A$2:$A$3001,$C$3,Registro!$K$2:$K$3001,$B19,Registro!$L$2:$L$3001,"Atendido")+SUMIFS(Registro!$J$2:$J$3001,Registro!$A$2:$A$3001,$C$3,Registro!$K$2:$K$3001,$B19,Registro!$L$2:$L$3001,"Atendido")) -> 0 | F19: Horas de silla perdidas | G19: =(SUMIFS(Registro!$U$2:$U$3001,Registro!$A$2:$A$3001,$C$3,Registro!$L$2:$L$3001,"No asistió")+SUMIFS(Registro!$U$2:$U$3001,Registro!$A$2:$A$3001,$C$3,Registro!$L$2:$L$3001,"Cancelado"))/60 -> 0
B20: =IF(Config!$H$8="","",Config!$H$8) -> Tarjeta débito | C20: =IF($B20="","",COUNTIFS(Registro!$A$2:$A$3001,$C$3,Registro!$K$2:$K$3001,$B20,Registro!$L$2:$L$3001,"Atendido")) -> 0 | D20: =IF($B20="","",SUMIFS(Registro!$I$2:$I$3001,Registro!$A$2:$A$3001,$C$3,Registro!$K$2:$K$3001,$B20,Registro!$L$2:$L$3001,"Atendido")+SUMIFS(Registro!$J$2:$J$3001,Registro!$A$2:$A$3001,$C$3,Registro!$K$2:$K$3001,$B20,Registro!$L$2:$L$3001,"Atendido")) -> 0
B21: =IF(Config!$H$9="","",Config!$H$9) -> Tarjeta crédito | C21: =IF($B21="","",COUNTIFS(Registro!$A$2:$A$3001,$C$3,Registro!$K$2:$K$3001,$B21,Registro!$L$2:$L$3001,"Atendido")) -> 0 | D21: =IF($B21="","",SUMIFS(Registro!$I$2:$I$3001,Registro!$A$2:$A$3001,$C$3,Registro!$K$2:$K$3001,$B21,Registro!$L$2:$L$3001,"Atendido")+SUMIFS(Registro!$J$2:$J$3001,Registro!$A$2:$A$3001,$C$3,Registro!$K$2:$K$3001,$B21,Registro!$L$2:$L$3001,"Atendido")) -> 0
B22: =IF(Config!$H$10="","",Config!$H$10) -> Transferencia | C22: =IF($B22="","",COUNTIFS(Registro!$A$2:$A$3001,$C$3,Registro!$K$2:$K$3001,$B22,Registro!$L$2:$L$3001,"Atendido")) -> 0 | D22: =IF($B22="","",SUMIFS(Registro!$I$2:$I$3001,Registro!$A$2:$A$3001,$C$3,Registro!$K$2:$K$3001,$B22,Registro!$L$2:$L$3001,"Atendido")+SUMIFS(Registro!$J$2:$J$3001,Registro!$A$2:$A$3001,$C$3,Registro!$K$2:$K$3001,$B22,Registro!$L$2:$L$3001,"Atendido")) -> 0
B23: =IF(Config!$H$11="","",Config!$H$11) -> Bold / Datáfono | C23: =IF($B23="","",COUNTIFS(Registro!$A$2:$A$3001,$C$3,Registro!$K$2:$K$3001,$B23,Registro!$L$2:$L$3001,"Atendido")) -> 0 | D23: =IF($B23="","",SUMIFS(Registro!$I$2:$I$3001,Registro!$A$2:$A$3001,$C$3,Registro!$K$2:$K$3001,$B23,Registro!$L$2:$L$3001,"Atendido")+SUMIFS(Registro!$J$2:$J$3001,Registro!$A$2:$A$3001,$C$3,Registro!$K$2:$K$3001,$B23,Registro!$L$2:$L$3001,"Atendido")) -> 0
B24: =IF(Config!$H$12="","",Config!$H$12) | C24: =IF($B24="","",COUNTIFS(Registro!$A$2:$A$3001,$C$3,Registro!$K$2:$K$3001,$B24,Registro!$L$2:$L$3001,"Atendido")) | D24: =IF($B24="","",SUMIFS(Registro!$I$2:$I$3001,Registro!$A$2:$A$3001,$C$3,Registro!$K$2:$K$3001,$B24,Registro!$L$2:$L$3001,"Atendido")+SUMIFS(Registro!$J$2:$J$3001,Registro!$A$2:$A$3001,$C$3,Registro!$K$2:$K$3001,$B24,Registro!$L$2:$L$3001,"Atendido"))
B25: =IF(Config!$H$13="","",Config!$H$13) | C25: =IF($B25="","",COUNTIFS(Registro!$A$2:$A$3001,$C$3,Registro!$K$2:$K$3001,$B25,Registro!$L$2:$L$3001,"Atendido")) | D25: =IF($B25="","",SUMIFS(Registro!$I$2:$I$3001,Registro!$A$2:$A$3001,$C$3,Registro!$K$2:$K$3001,$B25,Registro!$L$2:$L$3001,"Atendido")+SUMIFS(Registro!$J$2:$J$3001,Registro!$A$2:$A$3001,$C$3,Registro!$K$2:$K$3001,$B25,Registro!$L$2:$L$3001,"Atendido"))
B26: TOTAL RECAUDADO | C26: =SUM(C17:C25) -> 0 | D26: =SUM(D17:D25) -> 0
B27: Incluye propinas: es la plata que físicamente entró ese día.

Sheet Comisiones
B1: LIQUIDACIÓN DE COMISIONES POR MES
B3: Año: | C3: 2026
B4: Mes (1-12): | C4: 8
B6: Barbero | C6: Servicios | D6: Producido | E6: % Comisión | F6: Comisión | G6: Propinas | H6: TOTAL A PAGAR | I6: Neto barbería
B7: =IF(Config!$A$5="","",Config!$A$5) -> Rafael Castro | C7: =IF($B7="","",COUNTIFS(Registro!$Q$2:$Q$3001,$C$3,Registro!$R$2:$R$3001,$C$4,Registro!$C$2:$C$3001,$B7,Registro!$L$2:$L$3001,"Atendido")) -> 0 | D7: =IF($B7="","",SUMIFS(Registro!$I$2:$I$3001,Registro!$Q$2:$Q$3001,$C$3,Registro!$R$2:$R$3001,$C$4,Registro!$C$2:$C$3001,$B7,Registro!$L$2:$L$3001,"Atendido")) -> 0 | E7: =IF($B7="","",Config!$B$5) -> 0.5 | F7: =IF($B7="","",SUMIFS(Registro!$M$2:$M$3001,Registro!$Q$2:$Q$3001,$C$3,Registro!$R$2:$R$3001,$C$4,Registro!$C$2:$C$3001,$B7)) -> 0 | G7: =IF($B7="","",SUMIFS(Registro!$J$2:$J$3001,Registro!$Q$2:$Q$3001,$C$3,Registro!$R$2:$R$3001,$C$4,Registro!$C$2:$C$3001,$B7,Registro!$L$2:$L$3001,"Atendido")) -> 0 | H7: =IF($B7="","",SUMIFS(Registro!$N$2:$N$3001,Registro!$Q$2:$Q$3001,$C$3,Registro!$R$2:$R$3001,$C$4,Registro!$C$2:$C$3001,$B7)) -> 0 | I7: =IF($B7="","",SUMIFS(Registro!$O$2:$O$3001,Registro!$Q$2:$Q$3001,$C$3,Registro!$R$2:$R$3001,$C$4,Registro!$C$2:$C$3001,$B7)) -> 0
B8: =IF(Config!$A$6="","",Config!$A$6) -> Daniel Avila | C8: =IF($B8="","",COUNTIFS(Registro!$Q$2:$Q$3001,$C$3,Registro!$R$2:$R$3001,$C$4,Registro!$C$2:$C$3001,$B8,Registro!$L$2:$L$3001,"Atendido")) -> 0 | D8: =IF($B8="","",SUMIFS(Registro!$I$2:$I$3001,Registro!$Q$2:$Q$3001,$C$3,Registro!$R$2:$R$3001,$C$4,Registro!$C$2:$C$3001,$B8,Registro!$L$2:$L$3001,"Atendido")) -> 0 | E8: =IF($B8="","",Config!$B$6) -> 0.5 | F8: =IF($B8="","",SUMIFS(Registro!$M$2:$M$3001,Registro!$Q$2:$Q$3001,$C$3,Registro!$R$2:$R$3001,$C$4,Registro!$C$2:$C$3001,$B8)) -> 0 | G8: =IF($B8="","",SUMIFS(Registro!$J$2:$J$3001,Registro!$Q$2:$Q$3001,$C$3,Registro!$R$2:$R$3001,$C$4,Registro!$C$2:$C$3001,$B8,Registro!$L$2:$L$3001,"Atendido")) -> 0 | H8: =IF($B8="","",SUMIFS(Registro!$N$2:$N$3001,Registro!$Q$2:$Q$3001,$C$3,Registro!$R$2:$R$3001,$C$4,Registro!$C$2:$C$3001,$B8)) -> 0 | I8: =IF($B8="","",SUMIFS(Registro!$O$2:$O$3001,Registro!$Q$2:$Q$3001,$C$3,Registro!$R$2:$R$3001,$C$4,Registro!$C$2:$C$3001,$B8)) -> 0
B9: =IF(Config!$A$7="","",Config!$A$7) | C9: =IF($B9="","",COUNTIFS(Registro!$Q$2:$Q$3001,$C$3,Registro!$R$2:$R$3001,$C$4,Registro!$C$2:$C$3001,$B9,Registro!$L$2:$L$3001,"Atendido")) | D9: =IF($B9="","",SUMIFS(Registro!$I$2:$I$3001,Registro!$Q$2:$Q$3001,$C$3,Registro!$R$2:$R$3001,$C$4,Registro!$C$2:$C$3001,$B9,Registro!$L$2:$L$3001,"Atendido")) | E9: =IF($B9="","",Config!$B$7) | F9: =IF($B9="","",SUMIFS(Registro!$M$2:$M$3001,Registro!$Q$2:$Q$3001,$C$3,Registro!$R$2:$R$3001,$C$4,Registro!$C$2:$C$3001,$B9)) | G9: =IF($B9="","",SUMIFS(Registro!$J$2:$J$3001,Registro!$Q$2:$Q$3001,$C$3,Registro!$R$2:$R$3001,$C$4,Registro!$C$2:$C$3001,$B9,Registro!$L$2:$L$3001,"Atendido")) | H9: =IF($B9="","",SUMIFS(Registro!$N$2:$N$3001,Registro!$Q$2:$Q$3001,$C$3,Registro!$R$2:$R$3001,$C$4,Registro!$C$2:$C$3001,$B9)) | I9: =IF($B9="","",SUMIFS(Registro!$O$2:$O$3001,Registro!$Q$2:$Q$3001,$C$3,Registro!$R$2:$R$3001,$C$4,Registro!$C$2:$C$3001,$B9))
B10: =IF(Config!$A$8="","",Config!$A$8) | C10: =IF($B10="","",COUNTIFS(Registro!$Q$2:$Q$3001,$C$3,Registro!$R$2:$R$3001,$C$4,Registro!$C$2:$C$3001,$B10,Registro!$L$2:$L$3001,"Atendido")) | D10: =IF($B10="","",SUMIFS(Registro!$I$2:$I$3001,Registro!$Q$2:$Q$3001,$C$3,Registro!$R$2:$R$3001,$C$4,Registro!$C$2:$C$3001,$B10,Registro!$L$2:$L$3001,"Atendido")) | E10: =IF($B10="","",Config!$B$8) | F10: =IF($B10="","",SUMIFS(Registro!$M$2:$M$3001,Registro!$Q$2:$Q$3001,$C$3,Registro!$R$2:$R$3001,$C$4,Registro!$C$2:$C$3001,$B10)) | G10: =IF($B10="","",SUMIFS(Registro!$J$2:$J$3001,Registro!$Q$2:$Q$3001,$C$3,Registro!$R$2:$R$3001,$C$4,Registro!$C$2:$C$3001,$B10,Registro!$L$2:$L$3001,"Atendido")) | H10: =IF($B10="","",SUMIFS(Registro!$N$2:$N$3001,Registro!$Q$2:$Q$3001,$C$3,Registro!$R$2:$R$3001,$C$4,Registro!$C$2:$C$3001,$B10)) | I10: =IF($B10="","",SUMIFS(Registro!$O$2:$O$3001,Registro!$Q$2:$Q$3001,$C$3,Registro!$R$2:$R$3001,$C$4,Registro!$C$2:$C$3001,$B10))
B11: =IF(Config!$A$9="","",Config!$A$9) | C11: =IF($B11="","",COUNTIFS(Registro!$Q$2:$Q$3001,$C$3,Registro!$R$2:$R$3001,$C$4,Registro!$C$2:$C$3001,$B11,Registro!$L$2:$L$3001,"Atendido")) | D11: =IF($B11="","",SUMIFS(Registro!$I$2:$I$3001,Registro!$Q$2:$Q$3001,$C$3,Registro!$R$2:$R$3001,$C$4,Registro!$C$2:$C$3001,$B11,Registro!$L$2:$L$3001,"Atendido")) | E11: =IF($B11="","",Config!$B$9) | F11: =IF($B11="","",SUMIFS(Registro!$M$2:$M$3001,Registro!$Q$2:$Q$3001,$C$3,Registro!$R$2:$R$3001,$C$4,Registro!$C$2:$C$3001,$B11)) | G11: =IF($B11="","",SUMIFS(Registro!$J$2:$J$3001,Registro!$Q$2:$Q$3001,$C$3,Registro!$R$2:$R$3001,$C$4,Registro!$C$2:$C$3001,$B11,Registro!$L$2:$L$3001,"Atendido")) | H11: =IF($B11="","",SUMIFS(Registro!$N$2:$N$3001,Registro!$Q$2:$Q$3001,$C$3,Registro!$R$2:$R$3001,$C$4,Registro!$C$2:$C$3001,$B11)) | I11: =IF($B11="","",SUMIFS(Registro!$O$2:$O$3001,Registro!$Q$2:$Q$3001,$C$3,Registro!$R$2:$R$3001,$C$4,Registro!$C$2:$C$3001,$B11))
B12: =IF(Config!$A$10="","",Config!$A$10) | C12: =IF($B12="","",COUNTIFS(Registro!$Q$2:$Q$3001,$C$3,Registro!$R$2:$R$3001,$C$4,Registro!$C$2:$C$3001,$B12,Registro!$L$2:$L$3001,"Atendido")) | D12: =IF($B12="","",SUMIFS(Registro!$I$2:$I$3001,Registro!$Q$2:$Q$3001,$C$3,Registro!$R$2:$R$3001,$C$4,Registro!$C$2:$C$3001,$B12,Registro!$L$2:$L$3001,"Atendido")) | E12: =IF($B12="","",Config!$B$10) | F12: =IF($B12="","",SUMIFS(Registro!$M$2:$M$3001,Registro!$Q$2:$Q$3001,$C$3,Registro!$R$2:$R$3001,$C$4,Registro!$C$2:$C$3001,$B12)) | G12: =IF($B12="","",SUMIFS(Registro!$J$2:$J$3001,Registro!$Q$2:$Q$3001,$C$3,Registro!$R$2:$R$3001,$C$4,Registro!$C$2:$C$3001,$B12,Registro!$L$2:$L$3001,"Atendido")) | H12: =IF($B12="","",SUMIFS(Registro!$N$2:$N$3001,Registro!$Q$2:$Q$3001,$C$3,Registro!$R$2:$R$3001,$C$4,Registro!$C$2:$C$3001,$B12)) | I12: =IF($B12="","",SUMIFS(Registro!$O$2:$O$3001,Registro!$Q$2:$Q$3001,$C$3,Registro!$R$2:$R$3001,$C$4,Registro!$C$2:$C$3001,$B12))
B13: TOTAL MES | C13: =SUM(C7:C12) -> 0 | D13: =SUM(D7:D12) -> 0 | F13: =SUM(F7:F12) -> 0 | G13: =SUM(G7:G12) -> 0 | H13: =SUM(H7:H12) -> 0 | I13: =SUM(I7:I12) -> 0
B15: RESUMEN DEL MES
B16: Ingreso total por servicios | C16: =SUMIFS(Registro!$I$2:$I$3001,Registro!$Q$2:$Q$3001,$C$3,Registro!$R$2:$R$3001,$C$4,Registro!$L$2:$L$3001,"Atendido") -> 85000
B17: Total propinas (van al barbero) | C17: =SUMIFS(Registro!$J$2:$J$3001,Registro!$Q$2:$Q$3001,$C$3,Registro!$R$2:$R$3001,$C$4,Registro!$L$2:$L$3001,"Atendido") -> 0
B18: Total comisiones a pagar | C18: =SUMIFS(Registro!$M$2:$M$3001,Registro!$Q$2:$Q$3001,$C$3,Registro!$R$2:$R$3001,$C$4) -> 0
B19: Neto que queda en la barbería | C19: =SUMIFS(Registro!$O$2:$O$3001,Registro!$Q$2:$Q$3001,$C$3,Registro!$R$2:$R$3001,$C$4) -> 85000
B20: Servicios atendidos | C20: =COUNTIFS(Registro!$Q$2:$Q$3001,$C$3,Registro!$R$2:$R$3001,$C$4,Registro!$L$2:$L$3001,"Atendido") -> 1
B21: Ticket promedio | C21: =IFERROR(SUMIFS(Registro!$I$2:$I$3001,Registro!$Q$2:$Q$3001,$C$3,Registro!$R$2:$R$3001,$C$4,Registro!$L$2:$L$3001,"Atendido")/COUNTIFS(Registro!$Q$2:$Q$3001,$C$3,Registro!$R$2:$R$3001,$C$4,Registro!$L$2:$L$3001,"Atendido"),0) -> 85000
B22: Horas de silla vendidas | C22: =SUMIFS(Registro!$U$2:$U$3001,Registro!$Q$2:$Q$3001,$C$3,Registro!$R$2:$R$3001,$C$4,Registro!$L$2:$L$3001,"Atendido")/60 -> 1.25
B23: Ingreso por hora de silla | C23: =IFERROR(SUMIFS(Registro!$I$2:$I$3001,Registro!$Q$2:$Q$3001,$C$3,Registro!$R$2:$R$3001,$C$4,Registro!$L$2:$L$3001,"Atendido")/(SUMIFS(Registro!$U$2:$U$3001,Registro!$Q$2:$Q$3001,$C$3,Registro!$R$2:$R$3001,$C$4,Registro!$L$2:$L$3001,"Atendido")/60),0) -> 68000
B24: Citas perdidas (no asistió + cancelado) | C24: =COUNTIFS(Registro!$Q$2:$Q$3001,$C$3,Registro!$R$2:$R$3001,$C$4,Registro!$L$2:$L$3001,"No asistió")+COUNTIFS(Registro!$Q$2:$Q$3001,$C$3,Registro!$R$2:$R$3001,$C$4,Registro!$L$2:$L$3001,"Cancelado") -> 0
B25: Plata no realizada por citas perdidas | C25: =SUMIFS(Registro!$I$2:$I$3001,Registro!$Q$2:$Q$3001,$C$3,Registro!$R$2:$R$3001,$C$4,Registro!$L$2:$L$3001,"No asistió")+SUMIFS(Registro!$I$2:$I$3001,Registro!$Q$2:$Q$3001,$C$3,Registro!$R$2:$R$3001,$C$4,Registro!$L$2:$L$3001,"Cancelado") -> 0

Sheet Análisis
B1: ANÁLISIS HISTÓRICO
B2: La columna clave es INGRESO/HORA: cuánto genera cada servicio por hora de silla ocupada. Ahí está la decisión de precios y de agenda.
B4: POR SERVICIO | I4: POR DÍA DE LA SEMANA | M4: POR FRANJA HORARIA
B5: Servicio | C5: Cantidad | D5: Ingresos | E5: Ticket prom. | F5: Horas | G5: Ingreso/hora | I5: Día | J5: Servicios | K5: Ingresos | M5: Hora | N5: Servicios | O5: Ingresos
B6: =IF(Config!$D$5="","",Config!$D$5) -> Tinte (cambio de color) | C6: =IF($B6="","",COUNTIFS(Registro!$F$2:$F$3001,$B6,Registro!$L$2:$L$3001,"Atendido")) -> 0 | D6: =IF($B6="","",SUMIFS(Registro!$I$2:$I$3001,Registro!$F$2:$F$3001,$B6,Registro!$L$2:$L$3001,"Atendido")) -> 0 | E6: =IF($B6="","",IFERROR($D6/$C6,0)) -> 0 | F6: =IF($B6="","",SUMIFS(Registro!$U$2:$U$3001,Registro!$F$2:$F$3001,$B6,Registro!$L$2:$L$3001,"Atendido")/60) -> 0 | G6: =IF($B6="","",IFERROR(Config!$E5/(Config!$F5/60),0)) -> 83076.923 | I6: Lunes | J6: =COUNTIFS(Registro!$S$2:$S$3001,"Lunes",Registro!$L$2:$L$3001,"Atendido") -> 0 | K6: =SUMIFS(Registro!$I$2:$I$3001,Registro!$S$2:$S$3001,"Lunes",Registro!$L$2:$L$3001,"Atendido") -> 0 | M6: 7:00 - 8:00 | N6: =COUNTIFS(Registro!$T$2:$T$3001,7,Registro!$L$2:$L$3001,"Atendido") -> 0 | O6: =SUMIFS(Registro!$I$2:$I$3001,Registro!$T$2:$T$3001,7,Registro!$L$2:$L$3001,"Atendido") -> 0
B7: =IF(Config!$D$6="","",Config!$D$6) -> Corte y Barba Riif Experience | C7: =IF($B7="","",COUNTIFS(Registro!$F$2:$F$3001,$B7,Registro!$L$2:$L$3001,"Atendido")) -> 0 | D7: =IF($B7="","",SUMIFS(Registro!$I$2:$I$3001,Registro!$F$2:$F$3001,$B7,Registro!$L$2:$L$3001,"Atendido")) -> 0 | E7: =IF($B7="","",IFERROR($D7/$C7,0)) -> 0 | F7: =IF($B7="","",SUMIFS(Registro!$U$2:$U$3001,Registro!$F$2:$F$3001,$B7,Registro!$L$2:$L$3001,"Atendido")/60) -> 0 | G7: =IF($B7="","",IFERROR(Config!$E6/(Config!$F6/60),0)) -> 82500 | I7: Martes | J7: =COUNTIFS(Registro!$S$2:$S$3001,"Martes",Registro!$L$2:$L$3001,"Atendido") -> 0 | K7: =SUMIFS(Registro!$I$2:$I$3001,Registro!$S$2:$S$3001,"Martes",Registro!$L$2:$L$3001,"Atendido") -> 0 | M7: 8:00 - 9:00 | N7: =COUNTIFS(Registro!$T$2:$T$3001,8,Registro!$L$2:$L$3001,"Atendido") -> 0 | O7: =SUMIFS(Registro!$I$2:$I$3001,Registro!$T$2:$T$3001,8,Registro!$L$2:$L$3001,"Atendido") -> 0
B8: =IF(Config!$D$7="","",Config!$D$7) -> Corte y Barba VIP | C8: =IF($B8="","",COUNTIFS(Registro!$F$2:$F$3001,$B8,Registro!$L$2:$L$3001,"Atendido")) -> 1 | D8: =IF($B8="","",SUMIFS(Registro!$I$2:$I$3001,Registro!$F$2:$F$3001,$B8,Registro!$L$2:$L$3001,"Atendido")) -> 85000 | E8: =IF($B8="","",IFERROR($D8/$C8,0)) -> 85000 | F8: =IF($B8="","",SUMIFS(Registro!$U$2:$U$3001,Registro!$F$2:$F$3001,$B8,Registro!$L$2:$L$3001,"Atendido")/60) -> 1.25 | G8: =IF($B8="","",IFERROR(Config!$E7/(Config!$F7/60),0)) -> 68000 | I8: Miércoles | J8: =COUNTIFS(Registro!$S$2:$S$3001,"Miércoles",Registro!$L$2:$L$3001,"Atendido") -> 1 | K8: =SUMIFS(Registro!$I$2:$I$3001,Registro!$S$2:$S$3001,"Miércoles",Registro!$L$2:$L$3001,"Atendido") -> 85000 | M8: 9:00 - 10:00 | N8: =COUNTIFS(Registro!$T$2:$T$3001,9,Registro!$L$2:$L$3001,"Atendido") -> 0 | O8: =SUMIFS(Registro!$I$2:$I$3001,Registro!$T$2:$T$3001,9,Registro!$L$2:$L$3001,"Atendido") -> 0
B9: =IF(Config!$D$8="","",Config!$D$8) -> Tinte un Color | C9: =IF($B9="","",COUNTIFS(Registro!$F$2:$F$3001,$B9,Registro!$L$2:$L$3001,"Atendido")) -> 0 | D9: =IF($B9="","",SUMIFS(Registro!$I$2:$I$3001,Registro!$F$2:$F$3001,$B9,Registro!$L$2:$L$3001,"Atendido")) -> 0 | E9: =IF($B9="","",IFERROR($D9/$C9,0)) -> 0 | F9: =IF($B9="","",SUMIFS(Registro!$U$2:$U$3001,Registro!$F$2:$F$3001,$B9,Registro!$L$2:$L$3001,"Atendido")/60) -> 0 | G9: =IF($B9="","",IFERROR(Config!$E8/(Config!$F8/60),0)) -> 106666.67 | I9: Jueves | J9: =COUNTIFS(Registro!$S$2:$S$3001,"Jueves",Registro!$L$2:$L$3001,"Atendido") -> 0 | K9: =SUMIFS(Registro!$I$2:$I$3001,Registro!$S$2:$S$3001,"Jueves",Registro!$L$2:$L$3001,"Atendido") -> 0 | M9: 10:00 - 11:00 | N9: =COUNTIFS(Registro!$T$2:$T$3001,10,Registro!$L$2:$L$3001,"Atendido") -> 0 | O9: =SUMIFS(Registro!$I$2:$I$3001,Registro!$T$2:$T$3001,10,Registro!$L$2:$L$3001,"Atendido") -> 0
B10: =IF(Config!$D$9="","",Config!$D$9) -> Corte Riif Experience | C10: =IF($B10="","",COUNTIFS(Registro!$F$2:$F$3001,$B10,Registro!$L$2:$L$3001,"Atendido")) -> 0 | D10: =IF($B10="","",SUMIFS(Registro!$I$2:$I$3001,Registro!$F$2:$F$3001,$B10,Registro!$L$2:$L$3001,"Atendido")) -> 0 | E10: =IF($B10="","",IFERROR($D10/$C10,0)) -> 0 | F10: =IF($B10="","",SUMIFS(Registro!$U$2:$U$3001,Registro!$F$2:$F$3001,$B10,Registro!$L$2:$L$3001,"Atendido")/60) -> 0 | G10: =IF($B10="","",IFERROR(Config!$E9/(Config!$F9/60),0)) -> 50000 | I10: Viernes | J10: =COUNTIFS(Registro!$S$2:$S$3001,"Viernes",Registro!$L$2:$L$3001,"Atendido") -> 0 | K10: =SUMIFS(Registro!$I$2:$I$3001,Registro!$S$2:$S$3001,"Viernes",Registro!$L$2:$L$3001,"Atendido") -> 0 | M10: 11:00 - 12:00 | N10: =COUNTIFS(Registro!$T$2:$T$3001,11,Registro!$L$2:$L$3001,"Atendido") -> 0 | O10: =SUMIFS(Registro!$I$2:$I$3001,Registro!$T$2:$T$3001,11,Registro!$L$2:$L$3001,"Atendido") -> 0
B11: =IF(Config!$D$10="","",Config!$D$10) -> Tratamiento facial | C11: =IF($B11="","",COUNTIFS(Registro!$F$2:$F$3001,$B11,Registro!$L$2:$L$3001,"Atendido")) -> 0 | D11: =IF($B11="","",SUMIFS(Registro!$I$2:$I$3001,Registro!$F$2:$F$3001,$B11,Registro!$L$2:$L$3001,"Atendido")) -> 0 | E11: =IF($B11="","",IFERROR($D11/$C11,0)) -> 0 | F11: =IF($B11="","",SUMIFS(Registro!$U$2:$U$3001,Registro!$F$2:$F$3001,$B11,Registro!$L$2:$L$3001,"Atendido")/60) -> 0 | G11: =IF($B11="","",IFERROR(Config!$E10/(Config!$F10/60),0)) -> 60000 | I11: Sábado | J11: =COUNTIFS(Registro!$S$2:$S$3001,"Sábado",Registro!$L$2:$L$3001,"Atendido") -> 0 | K11: =SUMIFS(Registro!$I$2:$I$3001,Registro!$S$2:$S$3001,"Sábado",Registro!$L$2:$L$3001,"Atendido") -> 0 | M11: 12:00 - 13:00 | N11: =COUNTIFS(Registro!$T$2:$T$3001,12,Registro!$L$2:$L$3001,"Atendido") -> 0 | O11: =SUMIFS(Registro!$I$2:$I$3001,Registro!$T$2:$T$3001,12,Registro!$L$2:$L$3001,"Atendido") -> 0
B12: =IF(Config!$D$11="","",Config!$D$11) -> Corte y Barba | C12: =IF($B12="","",COUNTIFS(Registro!$F$2:$F$3001,$B12,Registro!$L$2:$L$3001,"Atendido")) -> 0 | D12: =IF($B12="","",SUMIFS(Registro!$I$2:$I$3001,Registro!$F$2:$F$3001,$B12,Registro!$L$2:$L$3001,"Atendido")) -> 0 | E12: =IF($B12="","",IFERROR($D12/$C12,0)) -> 0 | F12: =IF($B12="","",SUMIFS(Registro!$U$2:$U$3001,Registro!$F$2:$F$3001,$B12,Registro!$L$2:$L$3001,"Atendido")/60) -> 0 | G12: =IF($B12="","",IFERROR(Config!$E11/(Config!$F11/60),0)) -> 80000 | I12: Domingo | J12: =COUNTIFS(Registro!$S$2:$S$3001,"Domingo",Registro!$L$2:$L$3001,"Atendido") -> 0 | K12: =SUMIFS(Registro!$I$2:$I$3001,Registro!$S$2:$S$3001,"Domingo",Registro!$L$2:$L$3001,"Atendido") -> 0 | M12: 13:00 - 14:00 | N12: =COUNTIFS(Registro!$T$2:$T$3001,13,Registro!$L$2:$L$3001,"Atendido") -> 0 | O12: =SUMIFS(Registro!$I$2:$I$3001,Registro!$T$2:$T$3001,13,Registro!$L$2:$L$3001,"Atendido") -> 0
B13: =IF(Config!$D$12="","",Config!$D$12) -> Corte VIP | C13: =IF($B13="","",COUNTIFS(Registro!$F$2:$F$3001,$B13,Registro!$L$2:$L$3001,"Atendido")) -> 0 | D13: =IF($B13="","",SUMIFS(Registro!$I$2:$I$3001,Registro!$F$2:$F$3001,$B13,Registro!$L$2:$L$3001,"Atendido")) -> 0 | E13: =IF($B13="","",IFERROR($D13/$C13,0)) -> 0 | F13: =IF($B13="","",SUMIFS(Registro!$U$2:$U$3001,Registro!$F$2:$F$3001,$B13,Registro!$L$2:$L$3001,"Atendido")/60) -> 0 | G13: =IF($B13="","",IFERROR(Config!$E12/(Config!$F12/60),0)) -> 60000 | M13: 14:00 - 15:00 | N13: =COUNTIFS(Registro!$T$2:$T$3001,14,Registro!$L$2:$L$3001,"Atendido") -> 0 | O13: =SUMIFS(Registro!$I$2:$I$3001,Registro!$T$2:$T$3001,14,Registro!$L$2:$L$3001,"Atendido") -> 0
B14: =IF(Config!$D$13="","",Config!$D$13) -> Matizante | C14: =IF($B14="","",COUNTIFS(Registro!$F$2:$F$3001,$B14,Registro!$L$2:$L$3001,"Atendido")) -> 0 | D14: =IF($B14="","",SUMIFS(Registro!$I$2:$I$3001,Registro!$F$2:$F$3001,$B14,Registro!$L$2:$L$3001,"Atendido")) -> 0 | E14: =IF($B14="","",IFERROR($D14/$C14,0)) -> 0 | F14: =IF($B14="","",SUMIFS(Registro!$U$2:$U$3001,Registro!$F$2:$F$3001,$B14,Registro!$L$2:$L$3001,"Atendido")/60) -> 0 | G14: =IF($B14="","",IFERROR(Config!$E13/(Config!$F13/60),0)) -> 90000 | M14: 15:00 - 16:00 | N14: =COUNTIFS(Registro!$T$2:$T$3001,15,Registro!$L$2:$L$3001,"Atendido") -> 1 | O14: =SUMIFS(Registro!$I$2:$I$3001,Registro!$T$2:$T$3001,15,Registro!$L$2:$L$3001,"Atendido") -> 85000
B15: =IF(Config!$D$14="","",Config!$D$14) -> Barba VIP | C15: =IF($B15="","",COUNTIFS(Registro!$F$2:$F$3001,$B15,Registro!$L$2:$L$3001,"Atendido")) -> 0 | D15: =IF($B15="","",SUMIFS(Registro!$I$2:$I$3001,Registro!$F$2:$F$3001,$B15,Registro!$L$2:$L$3001,"Atendido")) -> 0 | E15: =IF($B15="","",IFERROR($D15/$C15,0)) -> 0 | F15: =IF($B15="","",SUMIFS(Registro!$U$2:$U$3001,Registro!$F$2:$F$3001,$B15,Registro!$L$2:$L$3001,"Atendido")/60) -> 0 | G15: =IF($B15="","",IFERROR(Config!$E14/(Config!$F14/60),0)) -> 60000 | M15: 16:00 - 17:00 | N15: =COUNTIFS(Registro!$T$2:$T$3001,16,Registro!$L$2:$L$3001,"Atendido") -> 0 | O15: =SUMIFS(Registro!$I$2:$I$3001,Registro!$T$2:$T$3001,16,Registro!$L$2:$L$3001,"Atendido") -> 0
B16: =IF(Config!$D$15="","",Config!$D$15) -> Barba + Tinte | C16: =IF($B16="","",COUNTIFS(Registro!$F$2:$F$3001,$B16,Registro!$L$2:$L$3001,"Atendido")) -> 0 | D16: =IF($B16="","",SUMIFS(Registro!$I$2:$I$3001,Registro!$F$2:$F$3001,$B16,Registro!$L$2:$L$3001,"Atendido")) -> 0 | E16: =IF($B16="","",IFERROR($D16/$C16,0)) -> 0 | F16: =IF($B16="","",SUMIFS(Registro!$U$2:$U$3001,Registro!$F$2:$F$3001,$B16,Registro!$L$2:$L$3001,"Atendido")/60) -> 0 | G16: =IF($B16="","",IFERROR(Config!$E15/(Config!$F15/60),0)) -> 80000 | M16: 17:00 - 18:00 | N16: =COUNTIFS(Registro!$T$2:$T$3001,17,Registro!$L$2:$L$3001,"Atendido") -> 0 | O16: =SUMIFS(Registro!$I$2:$I$3001,Registro!$T$2:$T$3001,17,Registro!$L$2:$L$3001,"Atendido") -> 0
B17: =IF(Config!$D$16="","",Config!$D$16) -> Corte de Cabello | C17: =IF($B17="","",COUNTIFS(Registro!$F$2:$F$3001,$B17,Registro!$L$2:$L$3001,"Atendido")) -> 0 | D17: =IF($B17="","",SUMIFS(Registro!$I$2:$I$3001,Registro!$F$2:$F$3001,$B17,Registro!$L$2:$L$3001,"Atendido")) -> 0 | E17: =IF($B17="","",IFERROR($D17/$C17,0)) -> 0 | F17: =IF($B17="","",SUMIFS(Registro!$U$2:$U$3001,Registro!$F$2:$F$3001,$B17,Registro!$L$2:$L$3001,"Atendido")/60) -> 0 | G17: =IF($B17="","",IFERROR(Config!$E16/(Config!$F16/60),0)) -> 60000 | M17: 18:00 - 19:00 | N17: =COUNTIFS(Registro!$T$2:$T$3001,18,Registro!$L$2:$L$3001,"Atendido") -> 0 | O17: =SUMIFS(Registro!$I$2:$I$3001,Registro!$T$2:$T$3001,18,Registro!$L$2:$L$3001,"Atendido") -> 0
B18: =IF(Config!$D$17="","",Config!$D$17) -> Barba | C18: =IF($B18="","",COUNTIFS(Registro!$F$2:$F$3001,$B18,Registro!$L$2:$L$3001,"Atendido")) -> 0 | D18: =IF($B18="","",SUMIFS(Registro!$I$2:$I$3001,Registro!$F$2:$F$3001,$B18,Registro!$L$2:$L$3001,"Atendido")) -> 0 | E18: =IF($B18="","",IFERROR($D18/$C18,0)) -> 0 | F18: =IF($B18="","",SUMIFS(Registro!$U$2:$U$3001,Registro!$F$2:$F$3001,$B18,Registro!$L$2:$L$3001,"Atendido")/60) -> 0 | G18: =IF($B18="","",IFERROR(Config!$E17/(Config!$F17/60),0)) -> 60000 | M18: 19:00 - 20:00 | N18: =COUNTIFS(Registro!$T$2:$T$3001,19,Registro!$L$2:$L$3001,"Atendido") -> 0 | O18: =SUMIFS(Registro!$I$2:$I$3001,Registro!$T$2:$T$3001,19,Registro!$L$2:$L$3001,"Atendido") -> 0
B19: =IF(Config!$D$18="","",Config!$D$18) -> Mascarilla puntos negros | C19: =IF($B19="","",COUNTIFS(Registro!$F$2:$F$3001,$B19,Registro!$L$2:$L$3001,"Atendido")) -> 0 | D19: =IF($B19="","",SUMIFS(Registro!$I$2:$I$3001,Registro!$F$2:$F$3001,$B19,Registro!$L$2:$L$3001,"Atendido")) -> 0 | E19: =IF($B19="","",IFERROR($D19/$C19,0)) -> 0 | F19: =IF($B19="","",SUMIFS(Registro!$U$2:$U$3001,Registro!$F$2:$F$3001,$B19,Registro!$L$2:$L$3001,"Atendido")/60) -> 0 | G19: =IF($B19="","",IFERROR(Config!$E18/(Config!$F18/60),0)) -> 48000 | M19: 20:00 - 21:00 | N19: =COUNTIFS(Registro!$T$2:$T$3001,20,Registro!$L$2:$L$3001,"Atendido") -> 0 | O19: =SUMIFS(Registro!$I$2:$I$3001,Registro!$T$2:$T$3001,20,Registro!$L$2:$L$3001,"Atendido") -> 0
B20: =IF(Config!$D$19="","",Config!$D$19) -> Peinado | C20: =IF($B20="","",COUNTIFS(Registro!$F$2:$F$3001,$B20,Registro!$L$2:$L$3001,"Atendido")) -> 0 | D20: =IF($B20="","",SUMIFS(Registro!$I$2:$I$3001,Registro!$F$2:$F$3001,$B20,Registro!$L$2:$L$3001,"Atendido")) -> 0 | E20: =IF($B20="","",IFERROR($D20/$C20,0)) -> 0 | F20: =IF($B20="","",SUMIFS(Registro!$U$2:$U$3001,Registro!$F$2:$F$3001,$B20,Registro!$L$2:$L$3001,"Atendido")/60) -> 0 | G20: =IF($B20="","",IFERROR(Config!$E19/(Config!$F19/60),0)) -> 80000 | M20: 21:00 - 22:00 | N20: =COUNTIFS(Registro!$T$2:$T$3001,21,Registro!$L$2:$L$3001,"Atendido") -> 0 | O20: =SUMIFS(Registro!$I$2:$I$3001,Registro!$T$2:$T$3001,21,Registro!$L$2:$L$3001,"Atendido") -> 0
B21: =IF(Config!$D$20="","",Config!$D$20) -> Bordes / Line-up | C21: =IF($B21="","",COUNTIFS(Registro!$F$2:$F$3001,$B21,Registro!$L$2:$L$3001,"Atendido")) -> 0 | D21: =IF($B21="","",SUMIFS(Registro!$I$2:$I$3001,Registro!$F$2:$F$3001,$B21,Registro!$L$2:$L$3001,"Atendido")) -> 0 | E21: =IF($B21="","",IFERROR($D21/$C21,0)) -> 0 | F21: =IF($B21="","",SUMIFS(Registro!$U$2:$U$3001,Registro!$F$2:$F$3001,$B21,Registro!$L$2:$L$3001,"Atendido")/60) -> 0 | G21: =IF($B21="","",IFERROR(Config!$E20/(Config!$F20/60),0)) -> 45000
B22: =IF(Config!$D$21="","",Config!$D$21) -> Cejas | C22: =IF($B22="","",COUNTIFS(Registro!$F$2:$F$3001,$B22,Registro!$L$2:$L$3001,"Atendido")) -> 0 | D22: =IF($B22="","",SUMIFS(Registro!$I$2:$I$3001,Registro!$F$2:$F$3001,$B22,Registro!$L$2:$L$3001,"Atendido")) -> 0 | E22: =IF($B22="","",IFERROR($D22/$C22,0)) -> 0 | F22: =IF($B22="","",SUMIFS(Registro!$U$2:$U$3001,Registro!$F$2:$F$3001,$B22,Registro!$L$2:$L$3001,"Atendido")/60) -> 0 | G22: =IF($B22="","",IFERROR(Config!$E21/(Config!$F21/60),0)) -> 40000
B23: =IF(Config!$D$22="","",Config!$D$22) | C23: =IF($B23="","",COUNTIFS(Registro!$F$2:$F$3001,$B23,Registro!$L$2:$L$3001,"Atendido")) | D23: =IF($B23="","",SUMIFS(Registro!$I$2:$I$3001,Registro!$F$2:$F$3001,$B23,Registro!$L$2:$L$3001,"Atendido")) | E23: =IF($B23="","",IFERROR($D23/$C23,0)) | F23: =IF($B23="","",SUMIFS(Registro!$U$2:$U$3001,Registro!$F$2:$F$3001,$B23,Registro!$L$2:$L$3001,"Atendido")/60) | G23: =IF($B23="","",IFERROR(Config!$E22/(Config!$F22/60),0))
B24: =IF(Config!$D$23="","",Config!$D$23) | C24: =IF($B24="","",COUNTIFS(Registro!$F$2:$F$3001,$B24,Registro!$L$2:$L$3001,"Atendido")) | D24: =IF($B24="","",SUMIFS(Registro!$I$2:$I$3001,Registro!$F$2:$F$3001,$B24,Registro!$L$2:$L$3001,"Atendido")) | E24: =IF($B24="","",IFERROR($D24/$C24,0)) | F24: =IF($B24="","",SUMIFS(Registro!$U$2:$U$3001,Registro!$F$2:$F$3001,$B24,Registro!$L$2:$L$3001,"Atendido")/60) | G24: =IF($B24="","",IFERROR(Config!$E23/(Config!$F23/60),0))
B25: =IF(Config!$D$24="","",Config!$D$24) | C25: =IF($B25="","",COUNTIFS(Registro!$F$2:$F$3001,$B25,Registro!$L$2:$L$3001,"Atendido")) | D25: =IF($B25="","",SUMIFS(Registro!$I$2:$I$3001,Registro!$F$2:$F$3001,$B25,Registro!$L$2:$L$3001,"Atendido")) | E25: =IF($B25="","",IFERROR($D25/$C25,0)) | F25: =IF($B25="","",SUMIFS(Registro!$U$2:$U$3001,Registro!$F$2:$F$3001,$B25,Registro!$L$2:$L$3001,"Atendido")/60) | G25: =IF($B25="","",IFERROR(Config!$E24/(Config!$F24/60),0))
B27: Ingreso/hora se calcula con el precio y la duración de la carta, así que ya tiene valor antes de registrar servicios.
B30: POR BARBERO (histórico) | J30: SALUD DEL NEGOCIO
B31: Barbero | C31: Servicios | D31: Producido | E31: Ticket prom. | F31: Horas | G31: Ingreso/hora | H31: No asistió | J31: Servicios atendidos (total) | K31: =COUNTIFS(Registro!$L$2:$L$3001,"Atendido") -> 1
B32: =IF(Config!$A$5="","",Config!$A$5) -> Rafael Castro | C32: =IF($B32="","",COUNTIFS(Registro!$C$2:$C$3001,$B32,Registro!$L$2:$L$3001,"Atendido")) -> 0 | D32: =IF($B32="","",SUMIFS(Registro!$I$2:$I$3001,Registro!$C$2:$C$3001,$B32,Registro!$L$2:$L$3001,"Atendido")) -> 0 | E32: =IF($B32="","",IFERROR($D32/$C32,0)) -> 0 | F32: =IF($B32="","",SUMIFS(Registro!$U$2:$U$3001,Registro!$C$2:$C$3001,$B32,Registro!$L$2:$L$3001,"Atendido")/60) -> 0 | G32: =IF($B32="","",IFERROR($D32/$F32,0)) -> 0 | H32: =IF($B32="","",COUNTIFS(Registro!$C$2:$C$3001,$B32,Registro!$L$2:$L$3001,"No asistió")) -> 0 | J32: Ingreso histórico | K32: =SUMIFS(Registro!$I$2:$I$3001,Registro!$L$2:$L$3001,"Atendido") -> 85000
B33: =IF(Config!$A$6="","",Config!$A$6) -> Daniel Avila | C33: =IF($B33="","",COUNTIFS(Registro!$C$2:$C$3001,$B33,Registro!$L$2:$L$3001,"Atendido")) -> 0 | D33: =IF($B33="","",SUMIFS(Registro!$I$2:$I$3001,Registro!$C$2:$C$3001,$B33,Registro!$L$2:$L$3001,"Atendido")) -> 0 | E33: =IF($B33="","",IFERROR($D33/$C33,0)) -> 0 | F33: =IF($B33="","",SUMIFS(Registro!$U$2:$U$3001,Registro!$C$2:$C$3001,$B33,Registro!$L$2:$L$3001,"Atendido")/60) -> 0 | G33: =IF($B33="","",IFERROR($D33/$F33,0)) -> 0 | H33: =IF($B33="","",COUNTIFS(Registro!$C$2:$C$3001,$B33,Registro!$L$2:$L$3001,"No asistió")) -> 0 | J33: Ticket promedio general | K33: =IFERROR(SUMIFS(Registro!$I$2:$I$3001,Registro!$L$2:$L$3001,"Atendido")/COUNTIFS(Registro!$L$2:$L$3001,"Atendido"),0) -> 85000
B34: =IF(Config!$A$7="","",Config!$A$7) | C34: =IF($B34="","",COUNTIFS(Registro!$C$2:$C$3001,$B34,Registro!$L$2:$L$3001,"Atendido")) | D34: =IF($B34="","",SUMIFS(Registro!$I$2:$I$3001,Registro!$C$2:$C$3001,$B34,Registro!$L$2:$L$3001,"Atendido")) | E34: =IF($B34="","",IFERROR($D34/$C34,0)) | F34: =IF($B34="","",SUMIFS(Registro!$U$2:$U$3001,Registro!$C$2:$C$3001,$B34,Registro!$L$2:$L$3001,"Atendido")/60) | G34: =IF($B34="","",IFERROR($D34/$F34,0)) | H34: =IF($B34="","",COUNTIFS(Registro!$C$2:$C$3001,$B34,Registro!$L$2:$L$3001,"No asistió")) | J34: Horas de silla vendidas | K34: =SUMIFS(Registro!$U$2:$U$3001,Registro!$L$2:$L$3001,"Atendido")/60 -> 1.25
B35: =IF(Config!$A$8="","",Config!$A$8) | C35: =IF($B35="","",COUNTIFS(Registro!$C$2:$C$3001,$B35,Registro!$L$2:$L$3001,"Atendido")) | D35: =IF($B35="","",SUMIFS(Registro!$I$2:$I$3001,Registro!$C$2:$C$3001,$B35,Registro!$L$2:$L$3001,"Atendido")) | E35: =IF($B35="","",IFERROR($D35/$C35,0)) | F35: =IF($B35="","",SUMIFS(Registro!$U$2:$U$3001,Registro!$C$2:$C$3001,$B35,Registro!$L$2:$L$3001,"Atendido")/60) | G35: =IF($B35="","",IFERROR($D35/$F35,0)) | H35: =IF($B35="","",COUNTIFS(Registro!$C$2:$C$3001,$B35,Registro!$L$2:$L$3001,"No asistió")) | J35: Ingreso por hora de silla | K35: =IFERROR(SUMIFS(Registro!$I$2:$I$3001,Registro!$L$2:$L$3001,"Atendido")/(SUMIFS(Registro!$U$2:$U$3001,Registro!$L$2:$L$3001,"Atendido")/60),0) -> 68000
B36: =IF(Config!$A$9="","",Config!$A$9) | C36: =IF($B36="","",COUNTIFS(Registro!$C$2:$C$3001,$B36,Registro!$L$2:$L$3001,"Atendido")) | D36: =IF($B36="","",SUMIFS(Registro!$I$2:$I$3001,Registro!$C$2:$C$3001,$B36,Registro!$L$2:$L$3001,"Atendido")) | E36: =IF($B36="","",IFERROR($D36/$C36,0)) | F36: =IF($B36="","",SUMIFS(Registro!$U$2:$U$3001,Registro!$C$2:$C$3001,$B36,Registro!$L$2:$L$3001,"Atendido")/60) | G36: =IF($B36="","",IFERROR($D36/$F36,0)) | H36: =IF($B36="","",COUNTIFS(Registro!$C$2:$C$3001,$B36,Registro!$L$2:$L$3001,"No asistió")) | J36: Citas perdidas | K36: =COUNTIFS(Registro!$L$2:$L$3001,"No asistió")+COUNTIFS(Registro!$L$2:$L$3001,"Cancelado") -> 0
B37: =IF(Config!$A$10="","",Config!$A$10) | C37: =IF($B37="","",COUNTIFS(Registro!$C$2:$C$3001,$B37,Registro!$L$2:$L$3001,"Atendido")) | D37: =IF($B37="","",SUMIFS(Registro!$I$2:$I$3001,Registro!$C$2:$C$3001,$B37,Registro!$L$2:$L$3001,"Atendido")) | E37: =IF($B37="","",IFERROR($D37/$C37,0)) | F37: =IF($B37="","",SUMIFS(Registro!$U$2:$U$3001,Registro!$C$2:$C$3001,$B37,Registro!$L$2:$L$3001,"Atendido")/60) | G37: =IF($B37="","",IFERROR($D37/$F37,0)) | H37: =IF($B37="","",COUNTIFS(Registro!$C$2:$C$3001,$B37,Registro!$L$2:$L$3001,"No asistió")) | J37: Tasa de citas perdidas | K37: =IFERROR((COUNTIFS(Registro!$L$2:$L$3001,"No asistió")+COUNTIFS(Registro!$L$2:$L$3001,"Cancelado"))/(COUNTIFS(Registro!$L$2:$L$3001,"Atendido")+COUNTIFS(Registro!$L$2:$L$3001,"No asistió")+COUNTIFS(Registro!$L$2:$L$3001,"Cancelado")),0) -> 0
J38: Total pagado en comisiones | K38: =SUM(Registro!$M$2:$M$3001) -> 0
J39: Neto acumulado barbería | K39: =SUM(Registro!$O$2:$O$3001) -> 85000
